{
    "MySql Dependecie Initialization": {
        "prefix": "ksp-MySqlDependecie",
        "body": [
          "<!-- MySQL Connector -->",
          "<dependency>",
          "<groupId>mysql</groupId>",
          "<artifactId>mysql-connector-java</artifactId>",
          "<scope>runtime</scope>",
          "</dependency>",
          ""
        ],
        "description": "MySql Dependecie Initialization"
      },

      "Swagger Dependecie Initialization": {
        "prefix": "ksp-SwaggerDependecie",
        "body": [
          "<!-- https://mvnrepository.com/artifact/io.springfox/springfox-swagger2 -->",
          "<dependency>",
          "<groupId>io.springfox</groupId>",
          "<artifactId>springfox-swagger2</artifactId>",
          "</dependency>",
          "",
          "<!-- https://mvnrepository.com/artifact/io.springfox/springfox-swagger-ui -->",
          "<dependency>",
          "<groupId>io.springfox</groupId>",
          "<artifactId>springfox-swagger-ui</artifactId>",
          "<version>2.9.2</version>",
          "</dependency>"
        ],
        "description": "Swagger Dependecie Initialization"
      }
    
}